pyspectator_tornado/__init__.py
pyspectator_tornado/web_app.py
pyspectator_tornado/web_server.py
pyspectator_tornado-1.1.2.data/scripts/start.py
pyspectator_tornado-1.1.2.dist-info/DESCRIPTION.rst
pyspectator_tornado-1.1.2.dist-info/METADATA
pyspectator_tornado-1.1.2.dist-info/RECORD
pyspectator_tornado-1.1.2.dist-info/WHEEL
pyspectator_tornado-1.1.2.dist-info/metadata.json
pyspectator_tornado-1.1.2.dist-info/top_level.txt
